sourmash_plugin_containment_search.py
sourmash_plugin_containment_search-0.5.0.dist-info/licenses/LICENSE
sourmash_plugin_containment_search-0.5.0.dist-info/METADATA
sourmash_plugin_containment_search-0.5.0.dist-info/WHEEL
sourmash_plugin_containment_search-0.5.0.dist-info/top_level.txt
sourmash_plugin_containment_search-0.5.0.dist-info/RECORD
