Metadata-Version: 2.4
Name: sourmash_plugin_containment_search
Version: 0.5.0
Summary: sourmash plugin for improved output of containment search for metagenomes - DEPRECATED
Requires-Python: >=3.8
License-File: LICENSE
Requires-Dist: sourmash<5,>=4.8.0
Requires-Dist: numpy
Dynamic: license-file
